LICENSE
README.md
pyproject.toml
setup.cfg
setup.py
envschema/__init__.py
envschema/casters.py
envschema/docs.py
envschema/errors.py
envschema/field.py
envschema/loader.py
envschema/schema.py
envschema.egg-info/PKG-INFO
envschema.egg-info/SOURCES.txt
envschema.egg-info/dependency_links.txt
envschema.egg-info/requires.txt
envschema.egg-info/top_level.txt
tests/test_casters.py
tests/test_docs.py
tests/test_errors.py
tests/test_field.py
tests/test_loader.py
tests/test_nested_schemas.py
tests/test_optional_types.py
tests/test_schema.py