Metadata-Version: 2.4
Name: envschema
Version: 1.0.0
Summary: Type-safe environment variables with automatic validation and documentation generation
Home-page: https://github.com/g7AzaZLO/envschema
Download-URL: https://github.com/g7AzaZLO/envschema/archive/v1.0.0.zip
Author: AzaZLO
Author-email: maloymeee@yandex.ru
License: Apache License 2.0
Classifier: Intended Audience :: Developers
Classifier: License :: OSI Approved :: Apache Software License
Classifier: Operating System :: OS Independent
Classifier: Programming Language :: Python :: 3
Classifier: Programming Language :: Python :: 3.10
Classifier: Programming Language :: Python :: 3.11
Classifier: Programming Language :: Python :: 3.12
Classifier: Programming Language :: Python :: 3.13
Classifier: Programming Language :: Python :: 3.14
License-File: LICENSE
Requires-Dist: python-dotenv>=1.0.0
Dynamic: author
Dynamic: author-email
Dynamic: classifier
Dynamic: description
Dynamic: description-content-type
Dynamic: download-url
Dynamic: home-page
Dynamic: license
Dynamic: license-file
Dynamic: requires-dist
Dynamic: summary
